{
Users: [
{
"id": 1,
"name": "Jason",
"surname": "Abbott",
"email": "penny@humphrey.cc"
},
{
"id": 2,
"name": "Nancy",
"surname": "Olson",
"email": "luis@wall.ng"
},
{
"id": 3,
"name": "Nicholas",
"surname": "McLean",
"email": "stanley@harrell.ie"
},
{
"id": 4,
"name": "Glenda",
"surname": "Weeks",
"email": "louis@lucas.ma"
},
{
"id": 5,
"name": "Joanna",
"surname": "Huffman",
"email": "warren@dawson.vc"
},
{
"id": 6,
"name": "Eddie",
"surname": "Kelley",
"email": "alison@lassiter.ng"
},
{
"id": 7,
"name": "Allen",
"surname": "Warren",
"email": "rita@james.ke"
},
{
"id": 8,
"name": "Kent",
"surname": "Sutherland",
"email": "wendy@honeycutt.sx"
},
{
"id": 9,
"name": "Hannah",
"surname": "Payne",
"email": "dan@lane.tg"
},
{
"id": 10,
"name": "Barbara",
"surname": "Wall",
"email": "carolyn@crane.br"
}
]
}